cholupdates/__init__.py
cholupdates-0.0.1.dist-info/LICENSE
cholupdates-0.0.1.dist-info/METADATA
cholupdates-0.0.1.dist-info/WHEEL
cholupdates-0.0.1.dist-info/top_level.txt
cholupdates-0.0.1.dist-info/RECORD
