Metadata-Version: 2.1
Name: cholupdates
Version: 0.0.1
Summary: Efficient Low-Rank Updates for Cholesky Decompositions
Home-page: https://github.com/marvinpfoertner/cholupdates
Author: Marvin Pförtner
Author-email: marvin.pfoertner@icloud.com
License: MIT
Keywords: low-rank,rank-1,rank,one,update,downdate,cholesky
Platform: any
Requires-Dist: numpy
Requires-Dist: scipy
Provides-Extra: formatting
Requires-Dist: black ; extra == 'formatting'
Requires-Dist: isort ; extra == 'formatting'
Provides-Extra: linting
Requires-Dist: pylint ; extra == 'linting'
Provides-Extra: testing
Requires-Dist: pytest ; extra == 'testing'
Requires-Dist: pytest-cov ; extra == 'testing'
